{
  "symbol": "AAPL",
  "dataPoints": [
    {
      "_id": "6081d7ab2f285f0bfc2404f4",
      "date": "2021-04-21T00:00:00.000Z",
      "close": "111"
    },
    {
      "_id": "6081d7ab2f285f0bfc2404f5",
      "date": "2021-04-20T00:00:00.000Z",
      "close": "110"
    },
    {
      "_id": "6081d7ab2f285f0bfc2404f6",
      "date": "2021-04-19T00:00:00.000Z",
      "close": "112"
    },
    {
      "_id": "6081d7ab2f285f0bfc2404f7",
      "date": "2021-04-16T00:00:00.000Z",
      "close": "111"
    },
    {
      "_id": "6081d7ab2f285f0bfc2404f8",
      "date": "2021-04-15T00:00:00.000Z",
      "close": "112"
    },
    {
      "_id": "6081d7ab2f285f0bfc2404f9",
      "date": "2021-04-14T00:00:00.000Z",
      "close": "109"
    }
  ]
}
